rhizo_widgets/__init__.py
rhizo_widgets-0.1.12.dist-info/WHEEL
rhizo_widgets-0.1.12.dist-info/METADATA
rhizo_widgets-0.1.12.dist-info/RECORD
