Metadata-Version: 2.1
Name: rhizo-widgets
Version: 0.1.12
Summary: 
Author: Andy Jefferson
Author-email: andy@rhizo.co
Requires-Python: >=3.6,<4.0
Classifier: Programming Language :: Python :: 3
Classifier: Programming Language :: Python :: 3.6
Classifier: Programming Language :: Python :: 3.7
Classifier: Programming Language :: Python :: 3.8
Classifier: Programming Language :: Python :: 3.9
Requires-Dist: ipywidgets (>=7.6.5,<8.0.0)
